{
    "base46": {
        "cargoLocks": null,
        "date": "2024-01-18",
        "extract": null,
        "name": "base46",
        "passthru": null,
        "pinned": false,
        "src": {
            "deepClone": false,
            "fetchSubmodules": false,
            "leaveDotGit": false,
            "name": null,
            "owner": "comfysage",
            "repo": "base46",
            "rev": "ea004cd1031bc8dd7b5fdefe4da7a95920abc4da",
            "sha256": "sha256-Eu/+jxM2tJKoI8CU1pUix3wFM4aMoEzz9jqkWYL51Cw=",
            "sparseCheckout": [],
            "type": "github"
        },
        "version": "ea004cd1031bc8dd7b5fdefe4da7a95920abc4da"
    },
    "chaivim": {
        "cargoLocks": null,
        "date": "2024-11-21",
        "extract": null,
        "name": "chaivim",
        "passthru": null,
        "pinned": false,
        "src": {
            "deepClone": false,
            "fetchSubmodules": false,
            "leaveDotGit": false,
            "name": null,
            "owner": "comfysage",
            "repo": "chaivim",
            "rev": "06efc4130adbe76e5b7747b6553beddc1ff43e92",
            "sha256": "sha256-PCeMapl5iB/BhDSdg9TMHTpkFdGqyBUAMkU13o6a1M8=",
            "sparseCheckout": [],
            "type": "github"
        },
        "version": "06efc4130adbe76e5b7747b6553beddc1ff43e92"
    },
    "evergarden": {
        "cargoLocks": null,
        "date": "2025-01-08",
        "extract": null,
        "name": "evergarden",
        "passthru": null,
        "pinned": false,
        "src": {
            "deepClone": false,
            "fetchSubmodules": false,
            "leaveDotGit": false,
            "name": null,
            "owner": "comfysage",
            "repo": "evergarden",
            "rev": "999f4b24be7fe70989be977db929b45bb40d1009",
            "sha256": "sha256-eev4EqTaHgmFSrMQXTDlNswwpNWEEhhf5vA0EIJgxw4=",
            "sparseCheckout": [],
            "type": "github"
        },
        "version": "999f4b24be7fe70989be977db929b45bb40d1009"
    },
    "fidget": {
        "cargoLocks": null,
        "date": "2025-01-08",
        "extract": null,
        "name": "fidget",
        "passthru": null,
        "pinned": false,
        "src": {
            "deepClone": false,
            "fetchSubmodules": false,
            "leaveDotGit": false,
            "name": null,
            "owner": "j-hui",
            "repo": "fidget.nvim",
            "rev": "a0abbf18084b77d28bc70e24752e4f4fd54aea17",
            "sha256": "sha256-o0za2NxFtzHZa7PRIm9U/P1/fwJrxS1G79ukdGLhJ4Q=",
            "sparseCheckout": [],
            "type": "github"
        },
        "version": "a0abbf18084b77d28bc70e24752e4f4fd54aea17"
    },
    "gitsigns": {
        "cargoLocks": null,
        "date": "2025-01-08",
        "extract": null,
        "name": "gitsigns",
        "passthru": null,
        "pinned": false,
        "src": {
            "deepClone": false,
            "fetchSubmodules": false,
            "leaveDotGit": false,
            "name": null,
            "owner": "lewis6991",
            "repo": "gitsigns.nvim",
            "rev": "2eaa30537365f6889c850bd46ef6f18ddf8fac70",
            "sha256": "sha256-K8FADpzw8sx895qswZIUdumxg+yhuYL9d+WjbXKecz8=",
            "sparseCheckout": [],
            "type": "github"
        },
        "version": "2eaa30537365f6889c850bd46ef6f18ddf8fac70"
    },
    "incline": {
        "cargoLocks": null,
        "date": "2024-05-16",
        "extract": null,
        "name": "incline",
        "passthru": null,
        "pinned": false,
        "src": {
            "deepClone": false,
            "fetchSubmodules": false,
            "leaveDotGit": false,
            "name": null,
            "owner": "b0o",
            "repo": "incline.nvim",
            "rev": "16fc9c073e3ea4175b66ad94375df6d73fc114c0",
            "sha256": "sha256-5DoIvIdAZV7ZgmQO2XmbM3G+nNn4tAumsShoN3rDGrs=",
            "sparseCheckout": [],
            "type": "github"
        },
        "version": "16fc9c073e3ea4175b66ad94375df6d73fc114c0"
    },
    "indent": {
        "cargoLocks": null,
        "date": "2024-12-04",
        "extract": null,
        "name": "indent",
        "passthru": null,
        "pinned": false,
        "src": {
            "deepClone": false,
            "fetchSubmodules": false,
            "leaveDotGit": false,
            "name": null,
            "owner": "lukas-reineke",
            "repo": "indent-blankline.nvim",
            "rev": "259357fa4097e232730341fa60988087d189193a",
            "sha256": "sha256-H3lUQZDvgj3a2STYeMUDiOYPe7rfsy08tJ4SlDd+LuE=",
            "sparseCheckout": [],
            "type": "github"
        },
        "version": "259357fa4097e232730341fa60988087d189193a"
    },
    "keymaps": {
        "cargoLocks": null,
        "date": "2024-03-12",
        "extract": null,
        "name": "keymaps",
        "passthru": null,
        "pinned": false,
        "src": {
            "deepClone": false,
            "fetchSubmodules": false,
            "leaveDotGit": false,
            "name": null,
            "owner": "comfysage",
            "repo": "keymaps.nvim",
            "rev": "62f10ae89dfcf065035c20ad3cda2c84f36e43ab",
            "sha256": "sha256-Wgh9uVmKtKOCwo+Z3IFTp6Bv0m4QIju3FVPlxsHRWBg=",
            "sparseCheckout": [],
            "type": "github"
        },
        "version": "62f10ae89dfcf065035c20ad3cda2c84f36e43ab"
    },
    "lazy.nvim": {
        "cargoLocks": null,
        "date": "2025-01-06",
        "extract": null,
        "name": "lazy.nvim",
        "passthru": null,
        "pinned": false,
        "src": {
            "deepClone": false,
            "fetchSubmodules": false,
            "leaveDotGit": false,
            "name": null,
            "owner": "folke",
            "repo": "lazy.nvim",
            "rev": "d8f26efd456190241afd1b0f5235fe6fdba13d4a",
            "sha256": "sha256-7npvUPMmQC6/Ywdcuxbmdboa8eJ1RNgZ+rzb3MeN0t0=",
            "sparseCheckout": [],
            "type": "github"
        },
        "version": "d8f26efd456190241afd1b0f5235fe6fdba13d4a"
    },
    "lspconfig": {
        "cargoLocks": null,
        "date": "2025-01-08",
        "extract": null,
        "name": "lspconfig",
        "passthru": null,
        "pinned": false,
        "src": {
            "deepClone": false,
            "fetchSubmodules": false,
            "leaveDotGit": false,
            "name": null,
            "owner": "neovim",
            "repo": "nvim-lspconfig",
            "rev": "88157521e890fe7fdf18bee22438875edd6300a6",
            "sha256": "sha256-QMjk1MQh3PwxTf/8o0pvoDafje1/pLsvYlcJdcv3xmg=",
            "sparseCheckout": [],
            "type": "github"
        },
        "version": "88157521e890fe7fdf18bee22438875edd6300a6"
    },
    "lualine": {
        "cargoLocks": null,
        "date": "2024-11-08",
        "extract": null,
        "name": "lualine",
        "passthru": null,
        "pinned": false,
        "src": {
            "deepClone": false,
            "fetchSubmodules": false,
            "leaveDotGit": false,
            "name": null,
            "owner": "nvim-lualine",
            "repo": "lualine.nvim",
            "rev": "2a5bae925481f999263d6f5ed8361baef8df4f83",
            "sha256": "sha256-IN6Qz3jGxUcylYiRTyd8j6me3pAoqJsJXtFUvph/6EI=",
            "sparseCheckout": [],
            "type": "github"
        },
        "version": "2a5bae925481f999263d6f5ed8361baef8df4f83"
    },
    "luasnip": {
        "cargoLocks": null,
        "date": "2025-01-04",
        "extract": null,
        "name": "luasnip",
        "passthru": null,
        "pinned": false,
        "src": {
            "deepClone": false,
            "fetchSubmodules": false,
            "leaveDotGit": false,
            "name": null,
            "owner": "L3MON4D3",
            "repo": "LuaSnip",
            "rev": "c9b9a22904c97d0eb69ccb9bab76037838326817",
            "sha256": "sha256-3ecm5SDTcSOh256xSQPHhddQfMpepiEIpv58fHXrVg0=",
            "sparseCheckout": [],
            "type": "github"
        },
        "version": "c9b9a22904c97d0eb69ccb9bab76037838326817"
    },
    "mini": {
        "cargoLocks": null,
        "date": "2025-01-07",
        "extract": null,
        "name": "mini",
        "passthru": null,
        "pinned": false,
        "src": {
            "deepClone": false,
            "fetchSubmodules": false,
            "leaveDotGit": false,
            "name": null,
            "owner": "echasnovski",
            "repo": "mini.nvim",
            "rev": "bac6c8bb77fe0a872719ea43c39e35c7c695f05e",
            "sha256": "sha256-akTWtZtlUheW2sTOh7XUTUKRdpkayOgONCGA38BQ4T4=",
            "sparseCheckout": [],
            "type": "github"
        },
        "version": "bac6c8bb77fe0a872719ea43c39e35c7c695f05e"
    },
    "null": {
        "cargoLocks": null,
        "date": "2025-01-08",
        "extract": null,
        "name": "null",
        "passthru": null,
        "pinned": false,
        "src": {
            "deepClone": false,
            "fetchSubmodules": false,
            "leaveDotGit": false,
            "name": null,
            "owner": "nvimtools",
            "repo": "none-ls.nvim",
            "rev": "7bebb35a05871aeb99825f29d869cbd9a46bdbba",
            "sha256": "sha256-R2M9bDGuokDWKoXjfDl4+CQk8NeTpMy2JRkhDyUPf94=",
            "sparseCheckout": [],
            "type": "github"
        },
        "version": "7bebb35a05871aeb99825f29d869cbd9a46bdbba"
    },
    "nvim-cmp": {
        "cargoLocks": null,
        "date": "2025-01-06",
        "extract": null,
        "name": "nvim-cmp",
        "passthru": null,
        "pinned": false,
        "src": {
            "deepClone": false,
            "fetchSubmodules": false,
            "leaveDotGit": false,
            "name": null,
            "owner": "hrsh7th",
            "repo": "nvim-cmp",
            "rev": "8c82d0bd31299dbff7f8e780f5e06d2283de9678",
            "sha256": "sha256-TmXpMgkPWXHn4+leojZg1V18wOiPDsKQeG1h8nGgVHo=",
            "sparseCheckout": [],
            "type": "github"
        },
        "version": "8c82d0bd31299dbff7f8e780f5e06d2283de9678"
    },
    "plenary": {
        "cargoLocks": null,
        "date": "2024-09-17",
        "extract": null,
        "name": "plenary",
        "passthru": null,
        "pinned": false,
        "src": {
            "deepClone": false,
            "fetchSubmodules": false,
            "leaveDotGit": false,
            "name": null,
            "owner": "nvim-lua",
            "repo": "plenary.nvim",
            "rev": "2d9b06177a975543726ce5c73fca176cedbffe9d",
            "sha256": "sha256-bmmPekAvuBvLQmrnnX0n+FRBqfVxBsObhxIEkDGAla4=",
            "sparseCheckout": [],
            "type": "github"
        },
        "version": "2d9b06177a975543726ce5c73fca176cedbffe9d"
    },
    "telescope": {
        "cargoLocks": null,
        "date": "2025-01-08",
        "extract": null,
        "name": "telescope",
        "passthru": null,
        "pinned": false,
        "src": {
            "deepClone": false,
            "fetchSubmodules": false,
            "leaveDotGit": false,
            "name": null,
            "owner": "nvim-telescope",
            "repo": "telescope.nvim",
            "rev": "415af52339215926d705cccc08145f3782c4d132",
            "sha256": "sha256-5y8srYKaAqFplMtDjsc8GdDF8yui5vCNMiOeFLrC/sM=",
            "sparseCheckout": [],
            "type": "github"
        },
        "version": "415af52339215926d705cccc08145f3782c4d132"
    },
    "telescope_fzf": {
        "cargoLocks": null,
        "date": "2024-12-12",
        "extract": null,
        "name": "telescope_fzf",
        "passthru": null,
        "pinned": false,
        "src": {
            "deepClone": false,
            "fetchSubmodules": false,
            "leaveDotGit": false,
            "name": null,
            "owner": "nvim-telescope",
            "repo": "telescope-fzf-native.nvim",
            "rev": "dae2eac9d91464448b584c7949a31df8faefec56",
            "sha256": "sha256-ZBYZncCVtuks6tV4hhqWvQ3PlKElSHuWAEpo9o48pj4=",
            "sparseCheckout": [],
            "type": "github"
        },
        "version": "dae2eac9d91464448b584c7949a31df8faefec56"
    },
    "telescope_select": {
        "cargoLocks": null,
        "date": "2023-12-04",
        "extract": null,
        "name": "telescope_select",
        "passthru": null,
        "pinned": false,
        "src": {
            "deepClone": false,
            "fetchSubmodules": false,
            "leaveDotGit": false,
            "name": null,
            "owner": "nvim-telescope",
            "repo": "telescope-ui-select.nvim",
            "rev": "6e51d7da30bd139a6950adf2a47fda6df9fa06d2",
            "sha256": "sha256-YRhNmmG4gx9Ht8JwjQfbTjJyTHEuZmtP6lqnhOsk8bE=",
            "sparseCheckout": [],
            "type": "github"
        },
        "version": "6e51d7da30bd139a6950adf2a47fda6df9fa06d2"
    },
    "todo_comments": {
        "cargoLocks": null,
        "date": "2024-09-16",
        "extract": null,
        "name": "todo_comments",
        "passthru": null,
        "pinned": false,
        "src": {
            "deepClone": false,
            "fetchSubmodules": false,
            "leaveDotGit": false,
            "name": null,
            "owner": "folke",
            "repo": "todo-comments.nvim",
            "rev": "ae0a2afb47cf7395dc400e5dc4e05274bf4fb9e0",
            "sha256": "sha256-EH4Sy7qNkzOgA1INFzrtsRfD79TgMqSbKUdundyw22w=",
            "sparseCheckout": [],
            "type": "github"
        },
        "version": "ae0a2afb47cf7395dc400e5dc4e05274bf4fb9e0"
    },
    "treesitter": {
        "cargoLocks": null,
        "date": "2025-01-08",
        "extract": null,
        "name": "treesitter",
        "passthru": null,
        "pinned": false,
        "src": {
            "deepClone": false,
            "fetchSubmodules": false,
            "leaveDotGit": false,
            "name": null,
            "owner": "nvim-treesitter",
            "repo": "nvim-treesitter",
            "rev": "8ca76960ae75e0a3bb231402558eb50e79433161",
            "sha256": "sha256-1TkCVuZ8G4/XHsl2MHrukrRY8sDacb84ZJXSqYuIATA=",
            "sparseCheckout": [],
            "type": "github"
        },
        "version": "8ca76960ae75e0a3bb231402558eb50e79433161"
    },
    "trouble": {
        "cargoLocks": null,
        "date": "2024-11-27",
        "extract": null,
        "name": "trouble",
        "passthru": null,
        "pinned": false,
        "src": {
            "deepClone": false,
            "fetchSubmodules": false,
            "leaveDotGit": false,
            "name": null,
            "owner": "folke",
            "repo": "trouble.nvim",
            "rev": "46cf952fc115f4c2b98d4e208ed1e2dce08c9bf6",
            "sha256": "sha256-JhnERZfma2JHFEn/DElVmrSU5KxM2asx3SJ+86lCfoo=",
            "sparseCheckout": [],
            "type": "github"
        },
        "version": "46cf952fc115f4c2b98d4e208ed1e2dce08c9bf6"
    },
    "whichkey": {
        "cargoLocks": null,
        "date": "2025-01-05",
        "extract": null,
        "name": "whichkey",
        "passthru": null,
        "pinned": false,
        "src": {
            "deepClone": false,
            "fetchSubmodules": false,
            "leaveDotGit": false,
            "name": null,
            "owner": "folke",
            "repo": "which-key.nvim",
            "rev": "1f8d414f61e0b05958c342df9b6a4c89ce268766",
            "sha256": "sha256-9V74V01dCqg1w5fpzzCmyfhR3/AYQg2MCIYkkjFv1go=",
            "sparseCheckout": [],
            "type": "github"
        },
        "version": "1f8d414f61e0b05958c342df9b6a4c89ce268766"
    },
    "yosu": {
        "cargoLocks": null,
        "date": "2024-06-17",
        "extract": null,
        "name": "yosu",
        "passthru": null,
        "pinned": false,
        "src": {
            "deepClone": false,
            "fetchSubmodules": false,
            "leaveDotGit": false,
            "name": null,
            "owner": "comfysage",
            "repo": "yosu.nvim",
            "rev": "553c8c526975c5107efde17950417f3738fbb72d",
            "sha256": "sha256-bic9o81gkDLFV2K1HeSMg4xHofOzqebfvSqHl41XHps=",
            "sparseCheckout": [],
            "type": "github"
        },
        "version": "553c8c526975c5107efde17950417f3738fbb72d"
    }
}